alfredcmd/__init__.py
alfredcmd/cli.py
alfredcmd/module_importer.py
alfredcmd-0.1.7.dist-info/DESCRIPTION.rst
alfredcmd-0.1.7.dist-info/METADATA
alfredcmd-0.1.7.dist-info/RECORD
alfredcmd-0.1.7.dist-info/WHEEL
alfredcmd-0.1.7.dist-info/entry_points.txt
alfredcmd-0.1.7.dist-info/metadata.json
alfredcmd-0.1.7.dist-info/top_level.txt
