Metadata-Version: 2.0
Name: alfredcmd
Version: 0.1.7
Summary: Aliases and custom commands manager and runner
Home-page: https://github.com/GustavoKatel/alfredcmd
Author: Gustavo Sampaio
Author-email: gbritosampaio@gmail.com
License: MIT license
Keywords: alfredcmd
Platform: UNKNOWN
Classifier: Development Status :: 2 - Pre-Alpha
Classifier: Intended Audience :: Developers
Classifier: License :: OSI Approved :: MIT License
Classifier: Natural Language :: English
Classifier: Programming Language :: Python :: 3
Classifier: Programming Language :: Python :: 3.4
Classifier: Programming Language :: Python :: 3.5
Classifier: Programming Language :: Python :: 3.6
Requires-Dist: toml (>=0.9.4)
